odoo/addons/connector_dicom_crm/README.rst
odoo/addons/connector_dicom_crm/__init__.py
odoo/addons/connector_dicom_crm/__manifest__.py
odoo/addons/connector_dicom_crm/i18n/connector_dicom_crm.pot
odoo/addons/connector_dicom_crm/i18n/es_CL.po
odoo/addons/connector_dicom_crm/models/__init__.py
odoo/addons/connector_dicom_crm/models/crm_lead.py
odoo/addons/connector_dicom_crm/readme/CONTRIBUTORS.rst
odoo/addons/connector_dicom_crm/readme/DESCRIPTION.rst
odoo/addons/connector_dicom_crm/readme/USAGE.rst
odoo/addons/connector_dicom_crm/static/description/icon.png
odoo/addons/connector_dicom_crm/static/description/index.html
odoo/addons/connector_dicom_crm/views/crm_lead_views.xml
odoo12_addon_connector_dicom_crm-12.0.1.0.0.99.dev3.dist-info/METADATA
odoo12_addon_connector_dicom_crm-12.0.1.0.0.99.dev3.dist-info/WHEEL
odoo12_addon_connector_dicom_crm-12.0.1.0.0.99.dev3.dist-info/top_level.txt
odoo12_addon_connector_dicom_crm-12.0.1.0.0.99.dev3.dist-info/RECORD
